setup.py
parse_requests/__init__.py
parse_requests.egg-info/PKG-INFO
parse_requests.egg-info/SOURCES.txt
parse_requests.egg-info/dependency_links.txt
parse_requests.egg-info/not-zip-safe
parse_requests.egg-info/requires.txt
parse_requests.egg-info/top_level.txt