Metadata-Version: 1.1
Name: parse-requests
Version: 1.0.4
Summary: parse-rest-python - A fast and simple Python library to interact with Parse.com REST API
Home-page: https://github.com/collegeappz/parse-requests
Author: Kien Pham
Author-email: kien@collegeappz.com
License: MIT
Keywords: parse.com parse api rest
Platform: any
Classifier: Development Status :: 5 - Production/Stable
Classifier: Environment :: Console
Classifier: Intended Audience :: Developers
Classifier: License :: OSI Approved :: MIT License
Classifier: Operating System :: OS Independent
Classifier: Programming Language :: Python :: 2
Classifier: Topic :: Software Development :: Quality Assurance
